pymbrewclient/__init__.py
pymbrewclient/cli.py
pymbrewclient/client.py
pymbrewclient/rest/__init__.py
pymbrewclient/rest/client.py
pymbrewclient/rest/models.py
pymbrewclient-1.0.10.dist-info/licenses/LICENSE
pymbrewclient-1.0.10.dist-info/METADATA
pymbrewclient-1.0.10.dist-info/WHEEL
pymbrewclient-1.0.10.dist-info/entry_points.txt
pymbrewclient-1.0.10.dist-info/top_level.txt
pymbrewclient-1.0.10.dist-info/RECORD
